searchandsort/__init__.py
searchandsort/search.py
searchandsort/sort.py
searchandsort-1.0.0.dist-info/METADATA
searchandsort-1.0.0.dist-info/WHEEL
searchandsort-1.0.0.dist-info/top_level.txt
searchandsort-1.0.0.dist-info/RECORD
