Metadata-Version: 2.4
Name: searchandsort
Version: 1.0.0
Summary: Python package for searching and sorting algorithms with time analysis
Author: M P Nithish Praba
License: MIT
Project-URL: Homepage, https://github.com/mpnithishpraba/PP1-Search-and-Sort
Requires-Python: >=3.7
